README.md
setup.cfg
setup.py
extract_facial/__init__.py
extract_facial/extractRoi.py
extract_facial/getEyeOpenClose.py
extract_facial/getEyeOpenCloseIris.py
extract_facial/getMouthOpenClose.py
extract_facial.egg-info/PKG-INFO
extract_facial.egg-info/SOURCES.txt
extract_facial.egg-info/dependency_links.txt
extract_facial.egg-info/requires.txt
extract_facial.egg-info/top_level.txt